{
  "userRating.ratingCountList": [
    {
      "k": [
        7,
        4,
        3,
        9,
        27
      ],
      "v": {
        "iphone": {
          "in": [
            "2025-07-14",
            "2025-07-15",
            "2025-07-16",
            "2025-07-17",
            "2025-07-18"
          ]
        },
        "ipad": {
          "in": [
            "2025-07-14",
            "2025-07-17",
            "2025-07-18"
          ]
        }
      }
    },
    {
      "k": [
        7,
        4,
        4,
        9,
        28
      ],
      "v": {
        "ipad": {
          "in": [
            "2025-07-19"
          ]
        }
      }
    }
  ]
}