{
  "userRating.ratingCountList": [
    {
      "k": [
        108,
        29,
        47,
        491,
        2853
      ],
      "v": {
        "iphone": {
          "jp": [
            "2025-09-01"
          ]
        },
        "ipad": {
          "jp": [
            "2025-09-01"
          ]
        }
      }
    },
    {
      "k": [
        5,
        4,
        6,
        18,
        198
      ],
      "v": {
        "iphone": {
          "in": [
            "2025-09-01"
          ]
        },
        "ipad": {
          "in": [
            "2025-09-01"
          ]
        }
      }
    },
    {
      "k": [
        0,
        0,
        1,
        20,
        129
      ],
      "v": {
        "iphone": {
          "mo": [
            "2025-09-01"
          ]
        }
      }
    },
    {
      "k": [
        22,
        5,
        15,
        204,
        1178
      ],
      "v": {
        "iphone": {
          "fr": [
            "2025-09-01"
          ]
        },
        "ipad": {
          "fr": [
            "2025-09-01"
          ]
        }
      }
    },
    {
      "k": [
        189,
        29,
        97,
        995,
        9652
      ],
      "v": {
        "iphone": {
          "us": [
            "2025-09-01"
          ]
        },
        "ipad": {
          "us": [
            "2025-09-01"
          ]
        }
      }
    },
    {
      "k": [
        14,
        1,
        8,
        116,
        660
      ],
      "v": {
        "iphone": {
          "ca": [
            "2025-09-01"
          ]
        },
        "ipad": {
          "ca": [
            "2025-09-01"
          ]
        }
      }
    },
    {
      "k": [
        9,
        2,
        5,
        17,
        293
      ],
      "v": {
        "iphone": {
          "sg": [
            "2025-09-01"
          ]
        },
        "ipad": {
          "sg": [
            "2025-09-01"
          ]
        }
      }
    },
    {
      "k": [
        79,
        7,
        10,
        149,
        1475
      ],
      "v": {
        "iphone": {
          "hk": [
            "2025-09-01"
          ]
        },
        "ipad": {
          "hk": [
            "2025-09-01"
          ]
        }
      }
    },
    {
      "k": [
        147,
        12,
        40,
        322,
        5580
      ],
      "v": {
        "iphone": {
          "tw": [
            "2025-09-01"
          ]
        },
        "ipad": {
          "tw": [
            "2025-09-01"
          ]
        }
      }
    }
  ]
}