{
  "userRating.ratingCountList": [
    {
      "k": [
        350,
        52,
        132,
        701,
        9285
      ],
      "v": {
        "iphone": {
          "fr": [
            "2025-10-20"
          ]
        }
      }
    },
    {
      "k": [
        11216,
        1571,
        2826,
        14304,
        419943
      ],
      "v": {
        "iphone": {
          "us": [
            "2025-10-20"
          ]
        }
      }
    },
    {
      "k": [
        1180,
        121,
        268,
        1615,
        30467
      ],
      "v": {
        "iphone": {
          "ca": [
            "2025-10-20"
          ]
        }
      }
    },
    {
      "k": [
        350,
        52,
        132,
        703,
        9304
      ],
      "v": {
        "iphone": {
          "fr": [
            "2025-10-21"
          ]
        }
      }
    },
    {
      "k": [
        11220,
        1573,
        2831,
        14322,
        420861
      ],
      "v": {
        "iphone": {
          "us": [
            "2025-10-21"
          ]
        }
      }
    },
    {
      "k": [
        1182,
        121,
        268,
        1615,
        30525
      ],
      "v": {
        "iphone": {
          "ca": [
            "2025-10-21"
          ]
        }
      }
    },
    {
      "k": [
        351,
        52,
        132,
        705,
        9338
      ],
      "v": {
        "iphone": {
          "fr": [
            "2025-10-22"
          ]
        }
      }
    },
    {
      "k": [
        11223,
        1574,
        2835,
        14338,
        421827
      ],
      "v": {
        "iphone": {
          "us": [
            "2025-10-22"
          ]
        }
      }
    },
    {
      "k": [
        1184,
        121,
        268,
        1617,
        30558
      ],
      "v": {
        "iphone": {
          "ca": [
            "2025-10-22"
          ]
        }
      }
    },
    {
      "k": [
        352,
        52,
        133,
        707,
        9391
      ],
      "v": {
        "iphone": {
          "fr": [
            "2025-10-23"
          ]
        }
      }
    },
    {
      "k": [
        11246,
        1576,
        2844,
        14397,
        425236
      ],
      "v": {
        "iphone": {
          "us": [
            "2025-10-23"
          ]
        }
      }
    },
    {
      "k": [
        1186,
        122,
        268,
        1619,
        30686
      ],
      "v": {
        "iphone": {
          "ca": [
            "2025-10-23"
          ]
        }
      }
    },
    {
      "k": [
        352,
        52,
        133,
        707,
        9413
      ],
      "v": {
        "iphone": {
          "fr": [
            "2025-10-24"
          ]
        }
      }
    },
    {
      "k": [
        11256,
        1577,
        2852,
        14420,
        426132
      ],
      "v": {
        "iphone": {
          "us": [
            "2025-10-24"
          ]
        }
      }
    },
    {
      "k": [
        1186,
        122,
        268,
        1619,
        30723
      ],
      "v": {
        "iphone": {
          "ca": [
            "2025-10-24"
          ]
        }
      }
    }
  ]
}