{
  "minimumWatchOSVersion": [
    {
      "k": "4.0",
      "v": {
        "iphone": {
          "mo": [
            "2025-10-20",
            "2025-10-21",
            "2025-10-22",
            "2025-10-23",
            "2025-10-24"
          ],
          "hk": [
            "2025-10-20",
            "2025-10-21",
            "2025-10-22",
            "2025-10-23",
            "2025-10-24"
          ],
          "cn": [
            "2025-10-20",
            "2025-10-21",
            "2025-10-22",
            "2025-10-23",
            "2025-10-24"
          ]
        }
      }
    }
  ],
  "userRating.ratingCountList": [
    {
      "k": [
        8,
        0,
        1,
        3,
        32
      ],
      "v": {
        "iphone": {
          "mo": [
            "2025-10-20",
            "2025-10-21",
            "2025-10-22",
            "2025-10-23",
            "2025-10-24"
          ]
        }
      }
    },
    {
      "k": [
        9,
        0,
        3,
        24,
        79
      ],
      "v": {
        "iphone": {
          "hk": [
            "2025-10-20",
            "2025-10-21",
            "2025-10-22",
            "2025-10-23",
            "2025-10-24"
          ]
        }
      }
    },
    {
      "k": [
        11456,
        4025,
        8135,
        27256,
        453179
      ],
      "v": {
        "iphone": {
          "cn": [
            "2025-10-20"
          ]
        }
      }
    },
    {
      "k": [
        11457,
        4025,
        8135,
        27255,
        453180
      ],
      "v": {
        "iphone": {
          "cn": [
            "2025-10-21"
          ]
        }
      }
    },
    {
      "k": [
        11457,
        4025,
        8135,
        27255,
        453182
      ],
      "v": {
        "iphone": {
          "cn": [
            "2025-10-22"
          ]
        }
      }
    },
    {
      "k": [
        11458,
        4025,
        8135,
        27254,
        453181
      ],
      "v": {
        "iphone": {
          "cn": [
            "2025-10-23",
            "2025-10-24"
          ]
        }
      }
    }
  ],
  "watchBundleId": [
    {
      "k": "com.yeelion.kwplayer.watchkitapp",
      "v": {
        "iphone": {
          "mo": [
            "2025-10-20",
            "2025-10-21",
            "2025-10-22",
            "2025-10-23",
            "2025-10-24"
          ],
          "hk": [
            "2025-10-20",
            "2025-10-21",
            "2025-10-22",
            "2025-10-23",
            "2025-10-24"
          ],
          "cn": [
            "2025-10-20",
            "2025-10-21",
            "2025-10-22",
            "2025-10-23",
            "2025-10-24"
          ]
        }
      }
    }
  ]
}