{
  "userRating.ratingCountList": [
    {
      "k": [
        5734,
        1730,
        3448,
        9419,
        147835
      ],
      "v": {
        "ipad": {
          "cn": [
            "2025-08-04"
          ]
        }
      }
    },
    {
      "k": [
        5734,
        1731,
        3450,
        9421,
        147869
      ],
      "v": {
        "ipad": {
          "cn": [
            "2025-08-05"
          ]
        }
      }
    },
    {
      "k": [
        5734,
        1731,
        3450,
        9419,
        147871
      ],
      "v": {
        "ipad": {
          "cn": [
            "2025-08-06"
          ]
        }
      }
    }
  ]
}