{
  "userRating.ratingCountList": [
    {
      "k": [
        1,
        1,
        1,
        9,
        72
      ],
      "v": {
        "ipad": {
          "mo": [
            "2025-10-10",
            "2025-10-11",
            "2025-10-12"
          ]
        }
      }
    },
    {
      "k": [
        6,
        5,
        17,
        41,
        300
      ],
      "v": {
        "ipad": {
          "hk": [
            "2025-10-10",
            "2025-10-11",
            "2025-10-12"
          ]
        }
      }
    },
    {
      "k": [
        13,
        4,
        20,
        32,
        340
      ],
      "v": {
        "ipad": {
          "tw": [
            "2025-10-11"
          ]
        }
      }
    },
    {
      "k": [
        800,
        561,
        868,
        1560,
        10879
      ],
      "v": {
        "ipad": {
          "in": [
            "2025-10-12"
          ]
        }
      }
    }
  ]
}