{
  "userRating.ratingCountList": [
    {
      "k": [
        318,
        219,
        766,
        2341,
        21537
      ],
      "v": {
        "iphone": {
          "cn": [
            "2025-02-17",
            "2025-02-18"
          ]
        }
      }
    },
    {
      "k": [
        1,
        1,
        2,
        8,
        63
      ],
      "v": {
        "iphone": {
          "sg": [
            "2025-02-17",
            "2025-02-18"
          ]
        }
      }
    },
    {
      "k": [
        318,
        220,
        766,
        2339,
        21534
      ],
      "v": {
        "iphone": {
          "cn": [
            "2025-02-19"
          ]
        }
      }
    },
    {
      "k": [
        316,
        220,
        766,
        2339,
        21534
      ],
      "v": {
        "iphone": {
          "cn": [
            "2025-02-20"
          ]
        }
      }
    },
    {
      "k": [
        316,
        220,
        766,
        2339,
        21541
      ],
      "v": {
        "iphone": {
          "cn": [
            "2025-02-21"
          ]
        }
      }
    },
    {
      "k": [
        316,
        221,
        768,
        2344,
        21567
      ],
      "v": {
        "iphone": {
          "cn": [
            "2025-02-23"
          ]
        }
      }
    },
    {
      "k": [
        317,
        221,
        769,
        2345,
        21587
      ],
      "v": {
        "iphone": {
          "cn": [
            "2025-02-24"
          ]
        }
      }
    },
    {
      "k": [
        317,
        221,
        770,
        2347,
        21618
      ],
      "v": {
        "iphone": {
          "cn": [
            "2025-02-27"
          ]
        }
      }
    },
    {
      "k": [
        5,
        2,
        8,
        27,
        213
      ],
      "v": {
        "iphone": {
          "hk": [
            "2025-02-28",
            "2025-03-01"
          ]
        }
      }
    },
    {
      "k": [
        0,
        0,
        0,
        3,
        36
      ],
      "v": {
        "iphone": {
          "mo": [
            "2025-02-28",
            "2025-03-01"
          ]
        }
      }
    },
    {
      "k": [
        317,
        221,
        770,
        2347,
        21627
      ],
      "v": {
        "iphone": {
          "cn": [
            "2025-02-28"
          ]
        }
      }
    },
    {
      "k": [
        316,
        221,
        771,
        2346,
        21613
      ],
      "v": {
        "iphone": {
          "cn": [
            "2025-03-01"
          ]
        }
      }
    },
    {
      "k": [
        316,
        221,
        771,
        2345,
        21603
      ],
      "v": {
        "iphone": {
          "cn": [
            "2025-03-02"
          ]
        }
      }
    },
    {
      "k": [
        319,
        222,
        773,
        2350,
        21637
      ],
      "v": {
        "iphone": {
          "cn": [
            "2025-03-03"
          ]
        }
      }
    },
    {
      "k": [
        319,
        223,
        773,
        2357,
        21665
      ],
      "v": {
        "iphone": {
          "cn": [
            "2025-03-04"
          ]
        }
      }
    },
    {
      "k": [
        319,
        223,
        773,
        2352,
        21656
      ],
      "v": {
        "iphone": {
          "cn": [
            "2025-03-05"
          ]
        }
      }
    },
    {
      "k": [
        319,
        223,
        774,
        2352,
        21669
      ],
      "v": {
        "iphone": {
          "cn": [
            "2025-03-06"
          ]
        }
      }
    },
    {
      "k": [
        319,
        223,
        774,
        2352,
        21671
      ],
      "v": {
        "iphone": {
          "cn": [
            "2025-03-07"
          ]
        }
      }
    },
    {
      "k": [
        319,
        223,
        774,
        2354,
        21680
      ],
      "v": {
        "iphone": {
          "cn": [
            "2025-03-08"
          ]
        }
      }
    },
    {
      "k": [
        320,
        223,
        775,
        2355,
        21689
      ],
      "v": {
        "iphone": {
          "cn": [
            "2025-03-09"
          ]
        }
      }
    },
    {
      "k": [
        323,
        224,
        776,
        2360,
        21737
      ],
      "v": {
        "iphone": {
          "cn": [
            "2025-03-10"
          ]
        }
      }
    },
    {
      "k": [
        324,
        225,
        778,
        2365,
        21789
      ],
      "v": {
        "iphone": {
          "cn": [
            "2025-03-11"
          ]
        }
      }
    },
    {
      "k": [
        324,
        225,
        780,
        2366,
        21800
      ],
      "v": {
        "iphone": {
          "cn": [
            "2025-03-12"
          ]
        }
      }
    },
    {
      "k": [
        0,
        0,
        0,
        3,
        37
      ],
      "v": {
        "iphone": {
          "mo": [
            "2025-03-13",
            "2025-03-25"
          ]
        }
      }
    },
    {
      "k": [
        324,
        225,
        781,
        2367,
        21815
      ],
      "v": {
        "iphone": {
          "cn": [
            "2025-03-13"
          ]
        }
      }
    },
    {
      "k": [
        324,
        225,
        781,
        2369,
        21823
      ],
      "v": {
        "iphone": {
          "cn": [
            "2025-03-14"
          ]
        }
      }
    },
    {
      "k": [
        324,
        226,
        783,
        2375,
        21874
      ],
      "v": {
        "iphone": {
          "cn": [
            "2025-03-15"
          ]
        }
      }
    },
    {
      "k": [
        324,
        226,
        785,
        2378,
        21908
      ],
      "v": {
        "iphone": {
          "cn": [
            "2025-03-16"
          ]
        }
      }
    },
    {
      "k": [
        324,
        226,
        788,
        2387,
        21958
      ],
      "v": {
        "iphone": {
          "cn": [
            "2025-03-17"
          ]
        }
      }
    },
    {
      "k": [
        326,
        227,
        793,
        2399,
        22054
      ],
      "v": {
        "iphone": {
          "cn": [
            "2025-03-18"
          ]
        }
      }
    },
    {
      "k": [
        326,
        227,
        793,
        2399,
        22065
      ],
      "v": {
        "iphone": {
          "cn": [
            "2025-03-19"
          ]
        }
      }
    },
    {
      "k": [
        328,
        227,
        794,
        2403,
        22086
      ],
      "v": {
        "iphone": {
          "cn": [
            "2025-03-20"
          ]
        }
      }
    },
    {
      "k": [
        330,
        227,
        796,
        2405,
        22117
      ],
      "v": {
        "iphone": {
          "cn": [
            "2025-03-22"
          ]
        }
      }
    },
    {
      "k": [
        330,
        227,
        797,
        2407,
        22133
      ],
      "v": {
        "iphone": {
          "cn": [
            "2025-03-23"
          ]
        }
      }
    },
    {
      "k": [
        331,
        228,
        797,
        2413,
        22181
      ],
      "v": {
        "iphone": {
          "cn": [
            "2025-03-24"
          ]
        }
      }
    },
    {
      "k": [
        331,
        228,
        800,
        2419,
        22235
      ],
      "v": {
        "iphone": {
          "cn": [
            "2025-03-25"
          ]
        }
      }
    },
    {
      "k": [
        0,
        0,
        0,
        3,
        38
      ],
      "v": {
        "iphone": {
          "mo": [
            "2025-03-26",
            "2025-03-27",
            "2025-04-20",
            "2025-04-29",
            "2025-05-17",
            "2025-05-27",
            "2025-05-28",
            "2025-05-29",
            "2025-06-01",
            "2025-06-02",
            "2025-06-03",
            "2025-06-04",
            "2025-06-05",
            "2025-06-10",
            "2025-06-14",
            "2025-06-22",
            "2025-06-27",
            "2025-06-28",
            "2025-07-01"
          ]
        }
      }
    },
    {
      "k": [
        331,
        228,
        802,
        2420,
        22260
      ],
      "v": {
        "iphone": {
          "cn": [
            "2025-03-26"
          ]
        }
      }
    },
    {
      "k": [
        331,
        228,
        803,
        2426,
        22285
      ],
      "v": {
        "iphone": {
          "cn": [
            "2025-03-27"
          ]
        }
      }
    },
    {
      "k": [
        332,
        228,
        803,
        2426,
        22317
      ],
      "v": {
        "iphone": {
          "cn": [
            "2025-03-28"
          ]
        }
      }
    },
    {
      "k": [
        332,
        228,
        804,
        2426,
        22347
      ],
      "v": {
        "iphone": {
          "cn": [
            "2025-03-29"
          ]
        }
      }
    },
    {
      "k": [
        333,
        228,
        804,
        2427,
        22362
      ],
      "v": {
        "iphone": {
          "cn": [
            "2025-03-30"
          ]
        }
      }
    },
    {
      "k": [
        333,
        228,
        808,
        2428,
        22393
      ],
      "v": {
        "iphone": {
          "cn": [
            "2025-03-31",
            "2025-04-01"
          ]
        }
      }
    },
    {
      "k": [
        334,
        228,
        810,
        2441,
        22559
      ],
      "v": {
        "iphone": {
          "cn": [
            "2025-04-02"
          ]
        }
      }
    },
    {
      "k": [
        334,
        228,
        812,
        2441,
        22592
      ],
      "v": {
        "iphone": {
          "cn": [
            "2025-04-03"
          ]
        }
      }
    },
    {
      "k": [
        335,
        228,
        813,
        2443,
        22616
      ],
      "v": {
        "iphone": {
          "cn": [
            "2025-04-04"
          ]
        }
      }
    },
    {
      "k": [
        335,
        228,
        814,
        2449,
        22665
      ],
      "v": {
        "iphone": {
          "cn": [
            "2025-04-05",
            "2025-04-06"
          ]
        }
      }
    },
    {
      "k": [
        336,
        229,
        817,
        2465,
        22804
      ],
      "v": {
        "iphone": {
          "cn": [
            "2025-04-07"
          ]
        }
      }
    },
    {
      "k": [
        336,
        229,
        821,
        2474,
        22922
      ],
      "v": {
        "iphone": {
          "cn": [
            "2025-04-08"
          ]
        }
      }
    },
    {
      "k": [
        338,
        229,
        822,
        2478,
        22947
      ],
      "v": {
        "iphone": {
          "cn": [
            "2025-04-09"
          ]
        }
      }
    },
    {
      "k": [
        339,
        229,
        822,
        2479,
        22953
      ],
      "v": {
        "iphone": {
          "cn": [
            "2025-04-10"
          ]
        }
      }
    },
    {
      "k": [
        339,
        229,
        823,
        2481,
        22977
      ],
      "v": {
        "iphone": {
          "cn": [
            "2025-04-11"
          ]
        }
      }
    },
    {
      "k": [
        339,
        229,
        823,
        2483,
        22986
      ],
      "v": {
        "iphone": {
          "cn": [
            "2025-04-12"
          ]
        }
      }
    },
    {
      "k": [
        341,
        229,
        826,
        2486,
        23034
      ],
      "v": {
        "iphone": {
          "cn": [
            "2025-04-13",
            "2025-04-14"
          ]
        }
      }
    },
    {
      "k": [
        341,
        230,
        830,
        2490,
        23130
      ],
      "v": {
        "iphone": {
          "cn": [
            "2025-04-15"
          ]
        }
      }
    },
    {
      "k": [
        342,
        230,
        833,
        2492,
        23196
      ],
      "v": {
        "iphone": {
          "cn": [
            "2025-04-16"
          ]
        }
      }
    },
    {
      "k": [
        342,
        230,
        835,
        2501,
        23273
      ],
      "v": {
        "iphone": {
          "cn": [
            "2025-04-17"
          ]
        }
      }
    },
    {
      "k": [
        342,
        231,
        835,
        2503,
        23305
      ],
      "v": {
        "iphone": {
          "cn": [
            "2025-04-18"
          ]
        }
      }
    },
    {
      "k": [
        342,
        230,
        835,
        2503,
        23319
      ],
      "v": {
        "iphone": {
          "cn": [
            "2025-04-19"
          ]
        }
      }
    },
    {
      "k": [
        343,
        230,
        835,
        2504,
        23338
      ],
      "v": {
        "iphone": {
          "cn": [
            "2025-04-20"
          ]
        }
      }
    },
    {
      "k": [
        343,
        231,
        838,
        2504,
        23373
      ],
      "v": {
        "iphone": {
          "cn": [
            "2025-04-21"
          ]
        }
      }
    },
    {
      "k": [
        345,
        231,
        841,
        2515,
        23466
      ],
      "v": {
        "iphone": {
          "cn": [
            "2025-04-22"
          ]
        }
      }
    },
    {
      "k": [
        345,
        231,
        841,
        2516,
        23484
      ],
      "v": {
        "iphone": {
          "cn": [
            "2025-04-23"
          ]
        }
      }
    },
    {
      "k": [
        345,
        231,
        841,
        2518,
        23504
      ],
      "v": {
        "iphone": {
          "cn": [
            "2025-04-24"
          ]
        }
      }
    },
    {
      "k": [
        345,
        231,
        842,
        2521,
        23529
      ],
      "v": {
        "iphone": {
          "cn": [
            "2025-04-25"
          ]
        }
      }
    },
    {
      "k": [
        346,
        232,
        843,
        2520,
        23564
      ],
      "v": {
        "iphone": {
          "cn": [
            "2025-04-26"
          ]
        }
      }
    },
    {
      "k": [
        346,
        232,
        844,
        2523,
        23583
      ],
      "v": {
        "iphone": {
          "cn": [
            "2025-04-27"
          ]
        }
      }
    },
    {
      "k": [
        346,
        232,
        845,
        2524,
        23604
      ],
      "v": {
        "iphone": {
          "cn": [
            "2025-04-28"
          ]
        }
      }
    },
    {
      "k": [
        347,
        232,
        846,
        2529,
        23648
      ],
      "v": {
        "iphone": {
          "cn": [
            "2025-04-29"
          ]
        }
      }
    },
    {
      "k": [
        347,
        232,
        846,
        2533,
        23695
      ],
      "v": {
        "iphone": {
          "cn": [
            "2025-04-30"
          ]
        }
      }
    },
    {
      "k": [
        348,
        232,
        846,
        2537,
        23728
      ],
      "v": {
        "iphone": {
          "cn": [
            "2025-05-01"
          ]
        }
      }
    },
    {
      "k": [
        348,
        232,
        848,
        2542,
        23781
      ],
      "v": {
        "iphone": {
          "cn": [
            "2025-05-02"
          ]
        }
      }
    },
    {
      "k": [
        348,
        232,
        848,
        2544,
        23799
      ],
      "v": {
        "iphone": {
          "cn": [
            "2025-05-03"
          ]
        }
      }
    },
    {
      "k": [
        349,
        234,
        855,
        2559,
        23903
      ],
      "v": {
        "iphone": {
          "cn": [
            "2025-05-04"
          ]
        }
      }
    },
    {
      "k": [
        350,
        234,
        858,
        2566,
        23960
      ],
      "v": {
        "iphone": {
          "cn": [
            "2025-05-05"
          ]
        }
      }
    },
    {
      "k": [
        351,
        236,
        859,
        2576,
        24044
      ],
      "v": {
        "iphone": {
          "cn": [
            "2025-05-06"
          ]
        }
      }
    },
    {
      "k": [
        351,
        236,
        861,
        2583,
        24074
      ],
      "v": {
        "iphone": {
          "cn": [
            "2025-05-07"
          ]
        }
      }
    },
    {
      "k": [
        1,
        1,
        3,
        9,
        67
      ],
      "v": {
        "iphone": {
          "sg": [
            "2025-05-09"
          ]
        }
      }
    },
    {
      "k": [
        352,
        237,
        862,
        2589,
        24119
      ],
      "v": {
        "iphone": {
          "cn": [
            "2025-05-10"
          ]
        }
      }
    },
    {
      "k": [
        352,
        238,
        865,
        2592,
        24131
      ],
      "v": {
        "iphone": {
          "cn": [
            "2025-05-11",
            "2025-05-12",
            "2025-05-13"
          ]
        }
      }
    },
    {
      "k": [
        352,
        238,
        870,
        2595,
        24210
      ],
      "v": {
        "iphone": {
          "cn": [
            "2025-05-15"
          ]
        }
      }
    },
    {
      "k": [
        352,
        238,
        872,
        2595,
        24219
      ],
      "v": {
        "iphone": {
          "cn": [
            "2025-05-16"
          ]
        }
      }
    },
    {
      "k": [
        353,
        238,
        872,
        2596,
        24232
      ],
      "v": {
        "iphone": {
          "cn": [
            "2025-05-17"
          ]
        }
      }
    },
    {
      "k": [
        353,
        238,
        872,
        2598,
        24238
      ],
      "v": {
        "iphone": {
          "cn": [
            "2025-05-18"
          ]
        }
      }
    },
    {
      "k": [
        353,
        237,
        873,
        2600,
        24275
      ],
      "v": {
        "iphone": {
          "cn": [
            "2025-05-19"
          ]
        }
      }
    },
    {
      "k": [
        353,
        237,
        873,
        2600,
        24283
      ],
      "v": {
        "iphone": {
          "cn": [
            "2025-05-20"
          ]
        }
      }
    },
    {
      "k": [
        354,
        238,
        873,
        2604,
        24324
      ],
      "v": {
        "iphone": {
          "cn": [
            "2025-05-21"
          ]
        }
      }
    },
    {
      "k": [
        356,
        238,
        873,
        2604,
        24337
      ],
      "v": {
        "iphone": {
          "cn": [
            "2025-05-22",
            "2025-05-23"
          ]
        }
      }
    },
    {
      "k": [
        357,
        238,
        873,
        2604,
        24379
      ],
      "v": {
        "iphone": {
          "cn": [
            "2025-05-24"
          ]
        }
      }
    },
    {
      "k": [
        358,
        238,
        876,
        2604,
        24396
      ],
      "v": {
        "iphone": {
          "cn": [
            "2025-05-25"
          ]
        }
      }
    },
    {
      "k": [
        358,
        238,
        877,
        2606,
        24410
      ],
      "v": {
        "iphone": {
          "cn": [
            "2025-05-26"
          ]
        }
      }
    },
    {
      "k": [
        5,
        2,
        8,
        28,
        219
      ],
      "v": {
        "iphone": {
          "hk": [
            "2025-05-27",
            "2025-05-28",
            "2025-05-29",
            "2025-06-03",
            "2025-06-04",
            "2025-06-06"
          ]
        }
      }
    },
    {
      "k": [
        358,
        238,
        878,
        2616,
        24470
      ],
      "v": {
        "iphone": {
          "cn": [
            "2025-05-28"
          ]
        }
      }
    },
    {
      "k": [
        358,
        238,
        878,
        2618,
        24487
      ],
      "v": {
        "iphone": {
          "cn": [
            "2025-05-29"
          ]
        }
      }
    },
    {
      "k": [
        357,
        241,
        876,
        2619,
        24543
      ],
      "v": {
        "iphone": {
          "cn": [
            "2025-05-30"
          ]
        }
      }
    },
    {
      "k": [
        357,
        239,
        876,
        2623,
        24573
      ],
      "v": {
        "iphone": {
          "cn": [
            "2025-05-31"
          ]
        }
      }
    },
    {
      "k": [
        360,
        240,
        878,
        2631,
        24631
      ],
      "v": {
        "iphone": {
          "cn": [
            "2025-06-01"
          ]
        }
      }
    },
    {
      "k": [
        360,
        240,
        881,
        2638,
        24686
      ],
      "v": {
        "iphone": {
          "cn": [
            "2025-06-02"
          ]
        }
      }
    },
    {
      "k": [
        362,
        241,
        888,
        2656,
        24884
      ],
      "v": {
        "iphone": {
          "cn": [
            "2025-06-03"
          ]
        }
      }
    },
    {
      "k": [
        362,
        242,
        885,
        2660,
        24955
      ],
      "v": {
        "iphone": {
          "cn": [
            "2025-06-04"
          ]
        }
      }
    },
    {
      "k": [
        362,
        242,
        885,
        2661,
        24970
      ],
      "v": {
        "iphone": {
          "cn": [
            "2025-06-05"
          ]
        }
      }
    },
    {
      "k": [
        363,
        242,
        886,
        2668,
        25031
      ],
      "v": {
        "iphone": {
          "cn": [
            "2025-06-06"
          ]
        }
      }
    },
    {
      "k": [
        364,
        242,
        888,
        2673,
        25076
      ],
      "v": {
        "iphone": {
          "cn": [
            "2025-06-07",
            "2025-06-08"
          ]
        }
      }
    },
    {
      "k": [
        366,
        246,
        894,
        2691,
        25265
      ],
      "v": {
        "iphone": {
          "cn": [
            "2025-06-09"
          ]
        }
      }
    },
    {
      "k": [
        370,
        245,
        896,
        2697,
        25329
      ],
      "v": {
        "iphone": {
          "cn": [
            "2025-06-10"
          ]
        }
      }
    },
    {
      "k": [
        371,
        244,
        898,
        2707,
        25360
      ],
      "v": {
        "iphone": {
          "cn": [
            "2025-06-11"
          ]
        }
      }
    },
    {
      "k": [
        371,
        244,
        899,
        2710,
        25391
      ],
      "v": {
        "iphone": {
          "cn": [
            "2025-06-12",
            "2025-06-13",
            "2025-06-14"
          ]
        }
      }
    },
    {
      "k": [
        5,
        2,
        8,
        28,
        220
      ],
      "v": {
        "iphone": {
          "hk": [
            "2025-06-14"
          ]
        }
      }
    },
    {
      "k": [
        372,
        246,
        906,
        2722,
        25496
      ],
      "v": {
        "iphone": {
          "cn": [
            "2025-06-15"
          ]
        }
      }
    },
    {
      "k": [
        372,
        246,
        907,
        2723,
        25506
      ],
      "v": {
        "iphone": {
          "cn": [
            "2025-06-16"
          ]
        }
      }
    },
    {
      "k": [
        374,
        249,
        907,
        2730,
        25601
      ],
      "v": {
        "iphone": {
          "cn": [
            "2025-06-17"
          ]
        }
      }
    },
    {
      "k": [
        375,
        249,
        908,
        2735,
        25673
      ],
      "v": {
        "iphone": {
          "cn": [
            "2025-06-18"
          ]
        }
      }
    },
    {
      "k": [
        376,
        248,
        909,
        2741,
        25722
      ],
      "v": {
        "iphone": {
          "cn": [
            "2025-06-19"
          ]
        }
      }
    },
    {
      "k": [
        377,
        248,
        910,
        2745,
        25738
      ],
      "v": {
        "iphone": {
          "cn": [
            "2025-06-20"
          ]
        }
      }
    },
    {
      "k": [
        378,
        248,
        911,
        2752,
        25817
      ],
      "v": {
        "iphone": {
          "cn": [
            "2025-06-21"
          ]
        }
      }
    },
    {
      "k": [
        380,
        248,
        912,
        2753,
        25866
      ],
      "v": {
        "iphone": {
          "cn": [
            "2025-06-22"
          ]
        }
      }
    },
    {
      "k": [
        381,
        248,
        916,
        2767,
        25962
      ],
      "v": {
        "iphone": {
          "cn": [
            "2025-06-23"
          ]
        }
      }
    },
    {
      "k": [
        382,
        248,
        917,
        2768,
        25976
      ],
      "v": {
        "iphone": {
          "cn": [
            "2025-06-24"
          ]
        }
      }
    },
    {
      "k": [
        384,
        248,
        918,
        2771,
        26023
      ],
      "v": {
        "iphone": {
          "cn": [
            "2025-06-25"
          ]
        }
      }
    },
    {
      "k": [
        385,
        247,
        920,
        2775,
        26103
      ],
      "v": {
        "iphone": {
          "cn": [
            "2025-06-26"
          ]
        }
      }
    },
    {
      "k": [
        385,
        247,
        920,
        2777,
        26125
      ],
      "v": {
        "iphone": {
          "cn": [
            "2025-06-27"
          ]
        }
      }
    },
    {
      "k": [
        388,
        246,
        920,
        2780,
        26175
      ],
      "v": {
        "iphone": {
          "cn": [
            "2025-06-28"
          ]
        }
      }
    },
    {
      "k": [
        389,
        246,
        921,
        2783,
        26197
      ],
      "v": {
        "iphone": {
          "cn": [
            "2025-06-29"
          ]
        }
      }
    },
    {
      "k": [
        389,
        246,
        923,
        2791,
        26283
      ],
      "v": {
        "iphone": {
          "cn": [
            "2025-06-30"
          ]
        }
      }
    },
    {
      "k": [
        390,
        249,
        927,
        2799,
        26377
      ],
      "v": {
        "iphone": {
          "cn": [
            "2025-07-01"
          ]
        }
      }
    }
  ]
}