{
  "userRating.ratingCountList": [
    {
      "k": [
        26,
        2,
        15,
        47,
        460
      ],
      "v": {
        "iphone": {
          "mo": [
            "2025-09-02",
            "2025-09-03"
          ]
        },
        "ipad": {
          "mo": [
            "2025-09-02",
            "2025-09-03"
          ]
        }
      }
    },
    {
      "k": [
        700,
        85,
        182,
        784,
        8801
      ],
      "v": {
        "iphone": {
          "hk": [
            "2025-09-02",
            "2025-09-03"
          ]
        },
        "ipad": {
          "hk": [
            "2025-09-02",
            "2025-09-03"
          ]
        }
      }
    },
    {
      "k": [
        2483,
        250,
        418,
        1449,
        26502
      ],
      "v": {
        "iphone": {
          "tw": [
            "2025-09-02"
          ]
        },
        "ipad": {
          "tw": [
            "2025-09-02"
          ]
        }
      }
    },
    {
      "k": [
        2484,
        250,
        418,
        1449,
        26502
      ],
      "v": {
        "iphone": {
          "tw": [
            "2025-09-03"
          ]
        },
        "ipad": {
          "tw": [
            "2025-09-03"
          ]
        }
      }
    }
  ]
}