{
  "userRating.ratingCountList": [
    {
      "k": [
        39,
        27,
        74,
        160,
        1484
      ],
      "v": {
        "ipad": {
          "tw": [
            "2025-10-25"
          ]
        }
      }
    },
    {
      "k": [
        39,
        27,
        75,
        160,
        1484
      ],
      "v": {
        "ipad": {
          "tw": [
            "2025-10-26"
          ]
        }
      }
    },
    {
      "k": [
        2,
        0,
        6,
        9,
        83
      ],
      "v": {
        "ipad": {
          "mo": [
            "2025-10-29",
            "2025-10-31"
          ]
        },
        "iphone": {
          "mo": [
            "2025-10-31"
          ]
        }
      }
    }
  ]
}